[
  {
    "ParameterKey": "Environment",
    "ParameterValue": "prod"
  },
  {
    "ParameterKey": "DeploymentBucket",
    "ParameterValue": "bloip-deployment-prod"
  },
  {
    "ParameterKey": "DomainName",
    "ParameterValue": "bloip.com"
  },
  {
    "ParameterKey": "SSLCertificateARN",
    "ParameterValue": ""
  },
  {
    "ParameterKey": "HostedZone",
    "ParameterValue": "bloip.com"
  },
  {
    "ParameterKey": "HostedZoneId",
    "ParameterValue": ""
  },
  {
    "ParameterKey": "CloudFrontZoneId",
    "ParameterValue": ""
  },
  {
    "ParameterKey": "InstanceType",
    "ParameterValue": "t3.medium"
  },
  {
    "ParameterKey": "AMI",
    "ParameterValue": ""
  },
  {
    "ParameterKey": "NumberOfEC2Instances",
    "ParameterValue": "1"
  },
  {
    "ParameterKey": "SSHKeyName",
    "ParameterValue": "dev-key"
  },
  { "ParameterKey": "HealthCheckPath",
    "ParameterValue": "HTTPS:8443/"
  },
  {
    "ParameterKey": "NotificationEmail",
    "ParameterValue": ""
  },
  {
    "ParameterKey": "ProxyCacheTimeSecs",
    "ParameterValue": "2"
  },
  {
    "ParameterKey": "ChangeId",
    "ParameterValue": "53"
  }
]
